spade_norms/__init__.py
spade_norms/spade_norms.py
spade_norms/actions/__init__.py
spade_norms/actions/normative_action.py
spade_norms/engines/__init__.py
spade_norms/engines/norm_engine.py
spade_norms/engines/reasoning_engine.py
spade_norms/norms/__init__.py
spade_norms/norms/norm.py
spade_norms/norms/norm_enums.py
spade_norms/norms/norm_trace.py
spade_norms/norms/norm_utils.py
spade_norms/norms/normative_response.py
spade_norms/norms_templates/norms_template.html
spade_norms-0.1.4.dist-info/AUTHORS.rst
spade_norms-0.1.4.dist-info/LICENSE
spade_norms-0.1.4.dist-info/METADATA
spade_norms-0.1.4.dist-info/WHEEL
spade_norms-0.1.4.dist-info/top_level.txt
spade_norms-0.1.4.dist-info/RECORD
