Metadata-Version: 2.1
Name: spade-norms
Version: 0.1.4
Summary: SPADE Normative Plugin
Home-page: https://github.com/javipalanca/spade_norms
Author: Javi Palanca
Author-email: jpalanca@dsic.upv.es
License: MIT license
Keywords: spade_norms
Classifier: Development Status :: 2 - Pre-Alpha
Classifier: Intended Audience :: Developers
Classifier: License :: OSI Approved :: MIT License
Classifier: Natural Language :: English
Classifier: Programming Language :: Python :: 3
Classifier: Programming Language :: Python :: 3.8
Classifier: Programming Language :: Python :: 3.9
Classifier: Programming Language :: Python :: 3.10
Classifier: Operating System :: MacOS :: MacOS X
Classifier: Operating System :: POSIX :: Linux
Classifier: Operating System :: Microsoft :: Windows
Classifier: Topic :: Scientific/Engineering :: Artificial Intelligence
Classifier: Topic :: Internet :: XMPP
Requires-Python: >=3.8
License-File: LICENSE
License-File: AUTHORS.rst
Requires-Dist: aiohttp (==3.10.5)
Requires-Dist: aiohttp-jinja2 (==1.5)
Requires-Dist: aioopenssl (==0.6.0)
Requires-Dist: aiosasl (==0.5.0)
Requires-Dist: aiosignal (==1.3.1)
Requires-Dist: aioxmpp (==0.13.3)
Requires-Dist: arrow (==1.2.3)
Requires-Dist: async-timeout (==4.0.2)
Requires-Dist: attrs (==23.1.0)
Requires-Dist: Babel (==2.12.1)
Requires-Dist: cffi (==1.15.1)
Requires-Dist: charset-normalizer (==3.1.0)
Requires-Dist: cryptography (==41.0.1)
Requires-Dist: dnspython (==2.3.0)
Requires-Dist: exceptiongroup (==1.1.1)
Requires-Dist: frozenlist (==1.3.3)
Requires-Dist: idna (==3.4)
Requires-Dist: iniconfig (==2.0.0)
Requires-Dist: Jinja2 (==3.0.3)
Requires-Dist: jinja2-time (==0.2.0)
Requires-Dist: lxml (==4.9.2)
Requires-Dist: MarkupSafe (==2.1.3)
Requires-Dist: multidict (==5.2.0)
Requires-Dist: packaging (==23.1)
Requires-Dist: pluggy (==1.2.0)
Requires-Dist: pyasn1 (==0.4.8)
Requires-Dist: pyasn1-modules (==0.2.8)
Requires-Dist: pycparser (==2.21)
Requires-Dist: pyOpenSSL (==23.2.0)
Requires-Dist: python-dateutil (==2.8.2)
Requires-Dist: pytz (==2022.1)
Requires-Dist: singletonify (==0.2.4)
Requires-Dist: six (==1.16.0)
Requires-Dist: sortedcollections (==2.1.0)
Requires-Dist: sortedcontainers (==2.4.0)
Requires-Dist: spade (>=3.3.2)
Requires-Dist: timeago (==1.0.16)
Requires-Dist: tomli (==2.0.1)
Requires-Dist: tzlocal (==5.0.1)
Requires-Dist: yarl (==1.9.2)
